LICENSE
README.rst
setup.py
bin/med2image
med2image/__init__.py
med2image/med2image.py
med2image.egg-info/PKG-INFO
med2image.egg-info/SOURCES.txt
med2image.egg-info/dependency_links.txt
med2image.egg-info/not-zip-safe
med2image.egg-info/requires.txt
med2image.egg-info/top_level.txt