Metadata-Version: 2.1
Name: med2image
Version: 2.4.4
Summary: (Python) utility to convert medical images to jpg and png
Home-page: https://github.com/FNNDSC/med2image
Author: FNNDSC
Author-email: dev@babymri.org
License: MIT
Platform: UNKNOWN
License-File: LICENSE
